quart_mongo/__init__.py
quart_mongo/const.py
quart_mongo/core.py
quart_mongo/helpers.py
quart_mongo/py.typed
quart_mongo/typing.py
quart_mongo/utils.py
quart_mongo/wrappers.py
quart_mongo-0.1.2.dist-info/LICENSE
quart_mongo-0.1.2.dist-info/METADATA
quart_mongo-0.1.2.dist-info/WHEEL
quart_mongo-0.1.2.dist-info/RECORD
