Metadata-Version: 2.1
Name: quart-mongo
Version: 0.1.2
Summary: Quart-Mongo bridges Quart, Motor, and Odmantic to create a powerful MongoDB extension for your Quart app.
Home-page: https://github.com/Quart-Addons/quart-mongo
License: MIT
Author: Chris Rood
Author-email: quart.addons@gmail.com
Requires-Python: >=3.8
Classifier: Development Status :: 3 - Alpha
Classifier: Environment :: Web Environment
Classifier: Intended Audience :: Developers
Classifier: License :: OSI Approved :: MIT License
Classifier: Operating System :: OS Independent
Classifier: Programming Language :: Python
Classifier: Programming Language :: Python :: 3
Classifier: Programming Language :: Python :: 3.8
Classifier: Programming Language :: Python :: 3.9
Classifier: Programming Language :: Python :: 3.10
Classifier: Programming Language :: Python :: 3.11
Classifier: Programming Language :: Python :: 3.12
Classifier: Topic :: Internet :: WWW/HTTP :: Dynamic Content
Classifier: Topic :: Software Development :: Libraries :: Python Modules
Requires-Dist: motor (>=3.5)
Requires-Dist: odmantic (>=1.0.0)
Requires-Dist: pydantic (>=2.5.0)
Requires-Dist: quart (>=0.19.0)
Requires-Dist: six (>=1.16.0)
Requires-Dist: types-six (>=1.16.21.20240513)
Project-URL: Repository, https://github.com/Quart-Addons/quart-mongo
